pltflow/__init__.py
pltflow/charts.py
pltflow/pipeplot.py
pltflow/graphs/__init__.py
pltflow/graphs/bars.py
pltflow/graphs/base_chart.py
pltflow/graphs/histograms.py
pltflow/graphs/plot.py
pltflow/styles/__init__.py
pltflow/styles/base.py
pltflow/styles/innocent.py
pltflow/styles/mkbhd.py
pltflow/styles/vox.py
pltflow/utils/__init__.py
pltflow/utils/colors.py
pltflow/utils/data_checks.py
pltflow/utils/styling.py
pltflow/utils/utils.py
pltflow/wrangling/__init__.py
pltflow/wrangling/grouping.py
pltflow-0.0.5.dist-info/METADATA
pltflow-0.0.5.dist-info/WHEEL
pltflow-0.0.5.dist-info/top_level.txt
pltflow-0.0.5.dist-info/RECORD
